LICENSE
MANIFEST.in
README.md
package.json
setup.py
dash_split_pane/DashSplitPane.py
dash_split_pane/__init__.py
dash_split_pane/_imports_.py
dash_split_pane/dash_split_pane.css
dash_split_pane/dash_split_pane.min.js
dash_split_pane/dash_split_pane.min.js.map
dash_split_pane/metadata.json
dash_split_pane/package-info.json
dash_split_pane.egg-info/PKG-INFO
dash_split_pane.egg-info/SOURCES.txt
dash_split_pane.egg-info/dependency_links.txt
dash_split_pane.egg-info/top_level.txt