Metadata-Version: 2.1
Name: dash-split-pane
Version: 0.0.2
Summary: A split pane for dash based on react split pane.
Home-page: UNKNOWN
Author: James Saunders <james@businessoptics.boz>
License: MIT
Platform: UNKNOWN
Classifier: Framework :: Dash
